{
  "schema_version": "h011-control-plane-manifest-v1",
  "base_main_sha": "afed8c36",
  "head_sha": "HEAD",
  "pipeline_version": "h011-integrity-v3",
  "cohort_id": "h011-v3-w300-vwap-structure-v2",
  "window_s": 300,
  "paper_only": true,
  "live_capital_locked": true,
  "orders_enabled": false,
  "raw_store_enabled": true,
  "snapshot_enabled": true,
  "lifecycle_enabled": true,
  "invariant_monitor_enabled": true,
  "drift_monitor_enabled": true,
  "stress_scenarios_enabled": true,
  "tests_passed": 48,
  "tests_failed": 0,
  "coverage_pct": 0.0,
  "replay_verified": true,
  "snapshot_determinism_verified": true,
  "lifecycle_chain_verified": true,
  "legacy_isolation_verified": true,
  "human_review_required": true,
  "created_by": "GLM-5.2"
}
